can4python/canframe_definition.py
can4python/caninterface_raw.py
can4python/exceptions.py
can4python/canframe.py
can4python/configuration.py
can4python/canbus.py
can4python/caninterface_bcm.py
can4python/constants.py
can4python/filehandler_kcd.py
can4python/version.py
can4python/cansignal.py
can4python/utilities.py
can4python/__init__.py
can4python-0.2.1.dist-info/DESCRIPTION.rst
can4python-0.2.1.dist-info/RECORD
can4python-0.2.1.dist-info/METADATA
can4python-0.2.1.dist-info/WHEEL
can4python-0.2.1.dist-info/top_level.txt
can4python-0.2.1.dist-info/metadata.json
