Metadata-Version: 2.0
Name: can4python
Version: 0.2.1
Summary: A package for handling CAN bus signals on Linux SocketCAN, for Python 3.3 and later.
Home-page: https://github.com/caran/can4python
Author: Jonas Berg
Author-email: caranopensource@semcon.com
License: BSD
Keywords: can4python
Platform: UNKNOWN
Classifier: Development Status :: 4 - Beta
Classifier: Intended Audience :: Developers
Classifier: License :: OSI Approved :: BSD License
Classifier: Natural Language :: English
Classifier: Operating System :: POSIX :: Linux
Classifier: Programming Language :: Python :: 3 :: Only
Classifier: Programming Language :: Python :: 3.3
Classifier: Programming Language :: Python :: 3.4
Classifier: Programming Language :: Python :: 3.5
Classifier: Topic :: Scientific/Engineering
Classifier: Topic :: Software Development :: Embedded Systems
Classifier: Topic :: Software Development :: Libraries
Classifier: Topic :: System :: Hardware :: Hardware Drivers
